jqed/__init__.py
jqed/jqed.py
jqed-0.1.4.dist-info/LICENSE
jqed-0.1.4.dist-info/METADATA
jqed-0.1.4.dist-info/WHEEL
jqed-0.1.4.dist-info/entry_points.txt
jqed-0.1.4.dist-info/top_level.txt
jqed-0.1.4.dist-info/RECORD
