Metadata-Version: 2.1
Name: jqed
Version: 0.1.4
Summary: Process JSON data interactively using JQ
Home-page: https://github.com/Wazzaps/jqed
Author: David Shlemayev
Author-email: david.shlemayev@gmail.com
License: UNKNOWN
Platform: UNKNOWN
Classifier: Programming Language :: Python :: 3
Classifier: Environment :: Console
Classifier: License :: OSI Approved :: GNU General Public License v3 (GPLv3)
Classifier: Operating System :: POSIX :: Linux
Classifier: Intended Audience :: End Users/Desktop
Classifier: Intended Audience :: Developers
Classifier: Intended Audience :: Science/Research
Classifier: Intended Audience :: System Administrators
Classifier: Topic :: Utilities
Classifier: Topic :: Scientific/Engineering :: Information Analysis
Classifier: Topic :: Text Processing
License-File: LICENSE
Requires-Dist: urwid (>=2.1)
Requires-Dist: urwid-readline (>=0.13)
